pythontrr/__init__.py
pythontrr/__main__.py
pythontrr/config.py
pythontrr/scraper.py
pythontrr/trr.py
pythontrr/utils.py
pythontrr/data/logs/config.txt
pythontrr/data/logs/history.txt
pythontrr/data/logs/result.txt
pythontrr/data/texts/the-adventures-of-sherlock-holmes:-a-case-of-identity.txt
pythontrr/data/texts/the-adventures-of-sherlock-holmes:-a-scandal-in-bohemia.txt
pythontrr/data/texts/the-adventures-of-sherlock-holmes:-the-adventure-of-the-beryl-coronet.txt
pythontrr/data/texts/the-adventures-of-sherlock-holmes:-the-adventure-of-the-blue-carbuncle.txt
pythontrr/data/texts/the-adventures-of-sherlock-holmes:-the-adventure-of-the-copper-beeches.txt
pythontrr/data/texts/the-adventures-of-sherlock-holmes:-the-adventure-of-the-engineer's-thumb.txt
pythontrr/data/texts/the-adventures-of-sherlock-holmes:-the-adventure-of-the-noble-bachelor.txt
pythontrr/data/texts/the-adventures-of-sherlock-holmes:-the-adventure-of-the-speckled-band.txt
pythontrr/data/texts/the-adventures-of-sherlock-holmes:-the-boscombe-valley-mystery.txt
pythontrr/data/texts/the-adventures-of-sherlock-holmes:-the-five-orange-pips.txt
pythontrr/data/texts/the-adventures-of-sherlock-holmes:-the-man-with-the-twisted-lip.txt
pythontrr/data/texts/the-adventures-of-sherlock-holmes:-the-red-headed-league.txt
pythontrr-1.0.1.dist-info/LICENSE
pythontrr-1.0.1.dist-info/METADATA
pythontrr-1.0.1.dist-info/WHEEL
pythontrr-1.0.1.dist-info/top_level.txt
pythontrr-1.0.1.dist-info/RECORD
