Metadata-Version: 2.1
Name: pythontrr
Version: 1.0.1
Summary: python-trr is a terminal app written in Python for typing practice.
Home-page: https://github.com/kaiwinut/python-trr
Author: Kai Wang
License: UNKNOWN
Project-URL: Bug Reports, https://github.com/kaiwinut/python-trr/issues
Project-URL: Source Code, https://github.com/kaiwinut/python-trr
Platform: UNKNOWN
Classifier: Programming Language :: Python :: 3
Classifier: Programming Language :: Python :: 3 :: Only
Classifier: Programming Language :: Python :: 3.7
Classifier: Programming Language :: Python :: 3.8
Classifier: Programming Language :: Python :: 3.9
Classifier: License :: OSI Approved :: MIT License
Classifier: Operating System :: OS Independent
Requires-Python: >=3.7
License-File: LICENSE
